npym/__init__.py
npym-1.0.1.dist-info/METADATA
npym-1.0.1.dist-info/WHEEL
npym-1.0.1.dist-info/RECORD
